odoo/addons/__init__.py
odoo/addons/contacts/__init__.py
odoo/addons/contacts/__manifest__.py
odoo/addons/contacts/i18n/af.po
odoo/addons/contacts/i18n/am.po
odoo/addons/contacts/i18n/ar.po
odoo/addons/contacts/i18n/bg.po
odoo/addons/contacts/i18n/bs.po
odoo/addons/contacts/i18n/ca.po
odoo/addons/contacts/i18n/cs.po
odoo/addons/contacts/i18n/da.po
odoo/addons/contacts/i18n/de.po
odoo/addons/contacts/i18n/el.po
odoo/addons/contacts/i18n/en_GB.po
odoo/addons/contacts/i18n/es.po
odoo/addons/contacts/i18n/et.po
odoo/addons/contacts/i18n/eu.po
odoo/addons/contacts/i18n/fa.po
odoo/addons/contacts/i18n/fi.po
odoo/addons/contacts/i18n/fo.po
odoo/addons/contacts/i18n/fr.po
odoo/addons/contacts/i18n/fr_CA.po
odoo/addons/contacts/i18n/gl.po
odoo/addons/contacts/i18n/gu.po
odoo/addons/contacts/i18n/he.po
odoo/addons/contacts/i18n/hr.po
odoo/addons/contacts/i18n/hu.po
odoo/addons/contacts/i18n/id.po
odoo/addons/contacts/i18n/is.po
odoo/addons/contacts/i18n/it.po
odoo/addons/contacts/i18n/ja.po
odoo/addons/contacts/i18n/ka.po
odoo/addons/contacts/i18n/kab.po
odoo/addons/contacts/i18n/ko.po
odoo/addons/contacts/i18n/lo.po
odoo/addons/contacts/i18n/lt.po
odoo/addons/contacts/i18n/lv.po
odoo/addons/contacts/i18n/mk.po
odoo/addons/contacts/i18n/mn.po
odoo/addons/contacts/i18n/nb.po
odoo/addons/contacts/i18n/ne.po
odoo/addons/contacts/i18n/nl.po
odoo/addons/contacts/i18n/nl_BE.po
odoo/addons/contacts/i18n/pl.po
odoo/addons/contacts/i18n/pt.po
odoo/addons/contacts/i18n/pt_BR.po
odoo/addons/contacts/i18n/ro.po
odoo/addons/contacts/i18n/ru.po
odoo/addons/contacts/i18n/sk.po
odoo/addons/contacts/i18n/sl.po
odoo/addons/contacts/i18n/sq.po
odoo/addons/contacts/i18n/sr.po
odoo/addons/contacts/i18n/sr@latin.po
odoo/addons/contacts/i18n/sv.po
odoo/addons/contacts/i18n/sw.po
odoo/addons/contacts/i18n/ta.po
odoo/addons/contacts/i18n/th.po
odoo/addons/contacts/i18n/tr.po
odoo/addons/contacts/i18n/uk.po
odoo/addons/contacts/i18n/vi.po
odoo/addons/contacts/i18n/zh_CN.po
odooku_odoo_contacts-11.0.7.dist-info/LICENSE
odooku_odoo_contacts-11.0.7.dist-info/METADATA
odooku_odoo_contacts-11.0.7.dist-info/WHEEL
odooku_odoo_contacts-11.0.7.dist-info/top_level.txt
odooku_odoo_contacts-11.0.7.dist-info/RECORD
